free_ocr/__init__.py
free_ocr/ocr.py
free_ocr-0.1.0.dist-info/LICENSE
free_ocr-0.1.0.dist-info/METADATA
free_ocr-0.1.0.dist-info/WHEEL
free_ocr-0.1.0.dist-info/top_level.txt
free_ocr-0.1.0.dist-info/RECORD
